texfunctions/generator.py
texfunctions-0.1.1.dist-info/METADATA
texfunctions-0.1.1.dist-info/WHEEL
texfunctions-0.1.1.dist-info/RECORD
