Metadata-Version: 2.3
Name: texfunctions
Version: 0.1.1
Summary: a package for generating tex in functional style (course assignment)
Author: Igor
Author-email: greafdorothy@yandex.com
Requires-Python: >=3.10
Classifier: Programming Language :: Python :: 3
Classifier: Programming Language :: Python :: 3.10
Classifier: Programming Language :: Python :: 3.11
Classifier: Programming Language :: Python :: 3.12
Classifier: Programming Language :: Python :: 3.13
